[
  {
    "py/object": "model.group.Group",
    "footer": "",
    "header": "",
    "id": null,
    "name": ""
  },
  {
    "py/object": "model.group.Group",
    "footer": "footer:,\\s7i@a@\\)r(To",
    "header": "header",
    "id": null,
    "name": "namex"
  },
  {
    "py/object": "model.group.Group",
    "footer": "footerB^le')7CZ *Y`Z*;",
    "header": "header;~l(mf=;om)m",
    "id": null,
    "name": "nameH~t\\ T;g"
  },
  {
    "py/object": "model.group.Group",
    "footer": "footer0r38zj2|M>&]xOked",
    "header": "header|={L& [",
    "id": null,
    "name": "nameSq%.d2  "
  },
  {
    "py/object": "model.group.Group",
    "footer": "footerq/jK ~'Fu%v?pq f",
    "header": "headerje48U'B+%mBssp",
    "id": null,
    "name": "nameQC/b"
  },
  {
    "py/object": "model.group.Group",
    "footer": "footerf:( k>$ wUgP",
    "header": "headerjIWtuPy5H8~",
    "id": null,
    "name": "nameJ,5-2tu>"
  },
  {
    "py/object": "model.group.Group",
    "footer": "footer ,qhOaW",
    "header": "headerQ>\"WGq",
    "id": null,
    "name": "name8%$rC"
  },
  {
    "py/object": "model.group.Group",
    "footer": "footert;",
    "header": "headerX\\FP;ns+i W",
    "id": null,
    "name": "name`\"OK("
  },
  {
    "py/object": "model.group.Group",
    "footer": "footer8\"/.iz+1 WL ",
    "header": "header]w*Z0;E } G?>-.",
    "id": null,
    "name": "namei#a"
  },
  {
    "py/object": "model.group.Group",
    "footer": "footerh 4I&LA",
    "header": "header4",
    "id": null,
    "name": "nameB\"g<YvarG"
  },
  {
    "py/object": "model.group.Group",
    "footer": "footer~^V 6xZ]lamwPT",
    "header": "header6Ke YM{\"+h2T9",
    "id": null,
    "name": "name"
  }
]